{
  "acceptanceCompliance": "PASS",
  "advisoryAsBlockingDrift": "ZERO",
  "artifactId": "X22_CONTOUR_CLOSE_SUMMARY_V1",
  "blockingSurfaceExpansion": false,
  "closeout": {
    "action01_freezeX22EvidencePacket": "DONE",
    "action02_recordX22ContourCloseSummary": "DONE",
    "action03_openNextContourRecord": "DONE"
  },
  "falseGreenStatus": "NOT_DETECTED",
  "gateDecision": "CLOSED",
  "nextTicket": {
    "gate": "GO_IF_X22_CLOSEOUT_ARTIFACT_SIGNED",
    "objective": "EXECUTE_FINAL_TRANSITION_WITH_CANON_LOCK_AND_NON_EXPANDING_BLOCKING_SURFACE",
    "priority": "P1",
    "tzId": "TZ_X22_FINAL_TRANSITION_001"
  },
  "offlineReleaseIntegrity": "LOCALLY_VERIFIABLE",
  "owner": "KIRILL_PLUS_CODEX",
  "repeatability": "PASS_THREE_OF_THREE",
  "schemaVersion": 1,
  "scopeCompliance": "PASS",
  "sourceFreezePacket": "docs/OPS/EVIDENCE/X22_CONTOUR/x22-contour-freeze-packet-v1.json",
  "status": "COMPLETED",
  "taskId": "TZ_X22_WS03_CONTOUR_CLOSEOUT_001",
  "updatedAtUtc": "2026-02-28T19:55:14.137Z",
  "verdict": "ACCEPTED"
}
